main.py
Semenar_Task_3-1.0.0.dist-info/METADATA
Semenar_Task_3-1.0.0.dist-info/WHEEL
Semenar_Task_3-1.0.0.dist-info/top_level.txt
Semenar_Task_3-1.0.0.dist-info/RECORD
