Metadata-Version: 2.1
Name: Semenar_Task_3
Version: 1.0.0
Summary: task_3
Author-email: Gleb <glebnikolenko9@gmail.com>
Requires-Python: >=3.6
Requires-Dist: pandas
